xarray_selafin/Serafin.py
xarray_selafin/Untitled-1.ipynb
xarray_selafin/__init__.py
xarray_selafin/data/Serafin_var2D.csv
xarray_selafin/data/Serafin_var3D.csv
xarray_selafin/extract_contours.py
xarray_selafin/variable/__init__.py
xarray_selafin/variable/variables_2d.py
xarray_selafin/variable/variables_3d.py
xarray_selafin/variable/variables_utils.py
xarray_selafin/xarray_backend.py
xarray_selafin-0.2.0.dist-info/LICENSE.txt
xarray_selafin-0.2.0.dist-info/METADATA
xarray_selafin-0.2.0.dist-info/WHEEL
xarray_selafin-0.2.0.dist-info/entry_points.txt
xarray_selafin-0.2.0.dist-info/RECORD
