Metadata-Version: 2.3
Name: xarray-selafin
Version: 0.2.0
Summary: 
Author: tomsail
Author-email: saillour.thomas@gmail.com
Requires-Python: >=3.10
Classifier: Programming Language :: Python :: 3
Classifier: Programming Language :: Python :: 3.10
Classifier: Programming Language :: Python :: 3.11
Classifier: Programming Language :: Python :: 3.12
Classifier: Programming Language :: Python :: 3.13
Requires-Dist: numpy
Requires-Dist: xarray
Project-URL: Repository, https://github.com/oceanmodeling/xarray-selafin/
